clark_biom.py
clark_biom-1.0.0.dist-info/DESCRIPTION.rst
clark_biom-1.0.0.dist-info/LICENSE.txt
clark_biom-1.0.0.dist-info/METADATA
clark_biom-1.0.0.dist-info/RECORD
clark_biom-1.0.0.dist-info/WHEEL
clark_biom-1.0.0.dist-info/entry_points.txt
clark_biom-1.0.0.dist-info/metadata.json
clark_biom-1.0.0.dist-info/namespace_packages.txt
clark_biom-1.0.0.dist-info/top_level.txt
