Metadata-Version: 2.0
Name: clark-biom
Version: 1.0.0
Summary: Create BIOM-format tables from CLARK abundance tables.
Home-page: https://github.com/smdabdoub/clark-biom
Author: Shareef M. Dabdoub
Author-email: dabdoub.2@osu.edu
License: MIT
Keywords: CLARK,BIOM,metagenomics,bioinformatics,taxonomy,taxonomic-classification
Platform: UNKNOWN
Classifier: Development Status :: 5 - Production/Stable
Classifier: Environment :: Console
Classifier: Intended Audience :: Science/Research
Classifier: License :: OSI Approved :: Apache Software License
Classifier: Operating System :: OS Independent
Classifier: Programming Language :: Python
Classifier: Programming Language :: Python :: 2
Classifier: Programming Language :: Python :: 3
Classifier: Topic :: Scientific/Engineering :: Bio-Informatics
Requires-Python: >=2.7.14
Requires-Dist: biom-format (>=2.1.5)
